dragonion/__init__.py
dragonion/__main__.py
dragonion/modules/__init__.py
dragonion/modules/cli/__init__.py
dragonion/modules/cli/main.py
dragonion/modules/tui/__init__.py
dragonion/modules/tui/authentication/__init__.py
dragonion/modules/tui/authentication/authentication.py
dragonion/modules/tui/authentication/utils/__init__.py
dragonion/modules/tui/authentication/utils/results.py
dragonion/modules/tui/authentication/widgets/__init__.py
dragonion/modules/tui/authentication/widgets/containers.py
dragonion/modules/tui/authentication/widgets/inputs.py
dragonion/modules/tui/chat/__init__.py
dragonion/modules/tui/chat/chat.py
dragonion/modules/tui/chat/utils/__init__.py
dragonion/modules/tui/chat/utils/handlers/__init__.py
dragonion/modules/tui/chat/utils/handlers/input/__init__.py
dragonion/modules/tui/chat/utils/handlers/input/command/__init__.py
dragonion/modules/tui/chat/utils/handlers/input/command/command.py
dragonion/modules/tui/chat/utils/handlers/input/command/commands/__init__.py
dragonion/modules/tui/chat/utils/handlers/input/command/commands/avatar.py
dragonion/modules/tui/chat/utils/handlers/input/command/commands/connect.py
dragonion/modules/tui/chat/utils/handlers/input/command/commands/disconnect.py
dragonion/modules/tui/chat/utils/handlers/input/command/commands/exit.py
dragonion/modules/tui/chat/utils/handlers/input/command/commands/help.py
dragonion/modules/tui/chat/utils/handlers/input/command/commands/helpers/__init__.py
dragonion/modules/tui/chat/utils/handlers/input/command/commands/helpers/socket.py
dragonion/modules/tui/chat/utils/handlers/input/command/commands/join.py
dragonion/modules/tui/chat/utils/handlers/input/command/commands/room.py
dragonion/modules/tui/chat/utils/handlers/input/general.py
dragonion/modules/tui/chat/utils/handlers/input/message.py
dragonion/modules/tui/chat/utils/tasks/__init__.py
dragonion/modules/tui/chat/utils/tasks/socket_handler/__init__.py
dragonion-1.0.3.dist-info/METADATA
dragonion-1.0.3.dist-info/WHEEL
dragonion-1.0.3.dist-info/entry_points.txt
dragonion-1.0.3.dist-info/RECORD
