Metadata-Version: 2.1
Name: dragonion
Version: 1.0.3
Summary: Most modern-looking, encrypted and functional in-console onion chat that you control!
Author: BarsTiger
Author-email: zxcbarstiger@gmail.com
Requires-Python: >=3.10,<3.12
Classifier: Programming Language :: Python :: 3
Classifier: Programming Language :: Python :: 3.10
Classifier: Programming Language :: Python :: 3.11
Requires-Dist: attrs (>=23.1.0,<24.0.0)
Requires-Dist: click (>=8.1.6,<9.0.0)
Requires-Dist: cryptography (>=42.0.7,<43.0.0)
Requires-Dist: dragonion-core (>=0.1.1,<0.2.0)
Requires-Dist: ezzthread (>=1.0.0,<2.0.0)
Requires-Dist: psutil (>=5.9.5,<6.0.0)
Requires-Dist: pynacl (>=1.5.0,<2.0.0)
Requires-Dist: pysocks (>=1.7.1,<2.0.0)
Requires-Dist: requests (>=2.31.0,<3.0.0)
Requires-Dist: sqlitedict (>=2.1.0,<3.0.0)
Requires-Dist: stem (>=1.8.2,<2.0.0)
Requires-Dist: textual (>=0.32.0,<0.33.0)
Requires-Dist: websockets (>=12.0,<13.0)
